mcp_chinese_time/__init__.py
mcp_chinese_time/__main__.py
mcp_chinese_time/parser.py
mcp_chinese_time/server.py
mcp_chinese_time-0.1.0.dist-info/METADATA
mcp_chinese_time-0.1.0.dist-info/WHEEL
mcp_chinese_time-0.1.0.dist-info/entry_points.txt
mcp_chinese_time-0.1.0.dist-info/licenses/LICENSE
mcp_chinese_time-0.1.0.dist-info/RECORD
