Metadata-Version: 2.4
Name: mcp-chinese-time
Version: 0.1.0
Summary: MCP server for parsing Chinese fuzzy time expressions to standard datetime formats
Project-URL: Homepage, https://github.com/weiyilan/mcp-chinese-time
Project-URL: Repository, https://github.com/weiyilan/mcp-chinese-time
Project-URL: Issues, https://github.com/weiyilan/mcp-chinese-time/issues
Author-email: Weiyilan <weiyilan@example.com>
License-Expression: MIT
License-File: LICENSE
Keywords: chinese,datetime,mcp,model-context-protocol,nlp,time-parsing
Classifier: Development Status :: 4 - Beta
Classifier: Intended Audience :: Developers
Classifier: License :: OSI Approved :: MIT License
Classifier: Programming Language :: Python :: 3
Classifier: Programming Language :: Python :: 3.10
Classifier: Programming Language :: Python :: 3.11
Classifier: Programming Language :: Python :: 3.12
Classifier: Topic :: Software Development :: Libraries :: Python Modules
Classifier: Topic :: Text Processing :: Linguistic
Requires-Python: >=3.10
Requires-Dist: fastmcp>=2.0
Requires-Dist: pydantic>=2.0
Requires-Dist: zhdate>=0.1
Provides-Extra: dev
Requires-Dist: pytest-asyncio>=0.21; extra == 'dev'
Requires-Dist: pytest>=7.0; extra == 'dev'
Requires-Dist: ruff>=0.1; extra == 'dev'
